<?xml version="1.0" encoding="UTF-8"?>
<alpino_ds version="1.3">
  <node begin="0" cat="top" end="16" id="0" rel="top">
    <node begin="0" cat="smain" end="15" id="1" rel="--">
      <node begin="0" cat="np" end="2" id="2" rel="su">
        <node begin="0" end="1" frame="determiner(de)" id="3" infl="de" lcat="detp" lemma="de" lwtype="bep" naamval="stan" npagr="rest" pos="det" postag="LID(bep,stan,rest)" pt="lid" rel="det" root="de" sense="de" word="De"/>
        <node begin="1" end="2" frame="noun(de,count,pl)" gen="de" getal="mv" graad="basis" id="4" lcat="np" lemma="Limburger" ntype="eigen" num="pl" pos="noun" postag="N(eigen,mv,basis)" pt="n" rel="hd" rnum="pl" root="Limburger" sense="Limburger" word="Limburgers"/>
      </node>
      <node begin="2" end="3" frame="verb(hebben,pl,pred_np)" id="5" infl="pl" lcat="smain" lemma="noemen" pos="verb" postag="WW(pv,tgw,mv)" pt="ww" pvagr="mv" pvtijd="tgw" rel="hd" root="noem" sc="pred_np" sense="noem" stype="declarative" tense="present" word="noemen" wvorm="pv"/>
      <node begin="3" cat="np" end="10" id="6" rel="obj1">
        <node begin="3" end="4" frame="determiner(het,nwh,nmod,pro,nparg,wkpro)" id="7" infl="het" lcat="detp" lemma="het" lwtype="bep" naamval="stan" npagr="evon" pos="det" postag="LID(bep,stan,evon)" pt="lid" rel="det" root="het" sense="het" wh="nwh" word="het"/>
        <node aform="base" begin="4" buiging="met-e" end="5" frame="adjective(e)" graad="basis" id="8" infl="e" lcat="ap" lemma="vier_jaarlijks" naamval="stan" pos="adj" positie="prenom" postag="ADJ(prenom,basis,met-e,stan)" pt="adj" rel="mod" root="vier_jaarlijks" sense="vier_jaarlijks" vform="adj" word="vierjaarlijkse"/>
        <node begin="5" cat="mwu" end="8" id="9" mwu_root="Wereld Muziek Concours" mwu_sense="Wereld Muziek Concours" rel="hd">
          <node begin="5" end="6" frame="proper_name(sg,'ORG')" id="10" lcat="np" lemma="Wereld" neclass="ORG" num="sg" pos="name" postag="SPEC(deeleigen)" pt="spec" rel="mwp" rnum="sg" root="Wereld" sense="Wereld" spectype="deeleigen" word="Wereld"/>
          <node begin="6" end="7" frame="proper_name(sg,'ORG')" id="11" lcat="np" lemma="Muziek" neclass="ORG" num="sg" pos="name" postag="SPEC(deeleigen)" pt="spec" rel="mwp" rnum="sg" root="Muziek" sense="Muziek" spectype="deeleigen" word="Muziek"/>
          <node begin="7" end="8" frame="proper_name(sg,'ORG')" id="12" lcat="np" lemma="Concours" neclass="ORG" num="sg" pos="name" postag="SPEC(deeleigen)" pt="spec" rel="mwp" rnum="sg" root="Concours" sense="Concours" spectype="deeleigen" word="Concours"/>
        </node>
        <node begin="8" cat="pp" end="10" id="13" rel="mod">
          <node begin="8" end="9" frame="preposition(in,[])" id="14" lcat="pp" lemma="in" pos="prep" postag="VZ(init)" pt="vz" rel="hd" root="in" sense="in" vztype="init" word="in"/>
          <node begin="9" end="10" frame="proper_name(sg,'LOC')" genus="onz" getal="ev" graad="basis" id="15" lcat="np" lemma="Kerkrade" naamval="stan" neclass="LOC" ntype="eigen" num="sg" pos="name" postag="N(eigen,ev,basis,onz,stan)" pt="n" rel="obj1" rnum="sg" root="Kerkrade" sense="Kerkrade" word="Kerkrade"/>
        </node>
      </node>
      <node begin="10" cat="np" end="15" id="16" rel="predc">
        <node begin="10" end="11" frame="determiner(het,nwh,nmod,pro,nparg,wkpro)" id="17" infl="het" lcat="detp" lemma="het" lwtype="bep" naamval="stan" npagr="evon" pos="det" postag="LID(bep,stan,evon)" pt="lid" rel="det" root="het" sense="het" wh="nwh" word="het"/>
        <node begin="11" end="12" frame="proper_name(sg,'ORG')" genus="onz" getal="ev" graad="basis" id="18" lcat="np" lemma="Wimbledon" naamval="stan" neclass="ORG" ntype="eigen" num="sg" pos="name" postag="N(eigen,ev,basis,onz,stan)" pt="n" rel="hd" rnum="sg" root="Wimbledon" sense="Wimbledon" word="Wimbledon"/>
        <node begin="12" cat="pp" end="15" id="19" rel="mod">
          <node begin="12" end="13" frame="preposition(van,[af,uit,vandaan,[af,aan]])" id="20" lcat="pp" lemma="van" pos="prep" postag="VZ(init)" pt="vz" rel="hd" root="van" sense="van" vztype="init" word="van"/>
          <node begin="13" cat="np" end="15" id="21" rel="obj1">
            <node begin="13" end="14" frame="determiner(de)" id="22" infl="de" lcat="detp" lemma="de" lwtype="bep" naamval="stan" npagr="rest" pos="det" postag="LID(bep,stan,rest)" pt="lid" rel="det" root="de" sense="de" word="de"/>
            <node begin="14" end="15" frame="noun(de,mass,sg)" gen="de" genus="zijd" getal="ev" graad="basis" id="23" lcat="np" lemma="blaas_muziek" naamval="stan" ntype="soort" num="sg" pos="noun" postag="N(soort,ev,basis,zijd,stan)" pt="n" rel="hd" rnum="sg" root="blaas_muziek" sense="blaas_muziek" word="blaasmuziek"/>
          </node>
        </node>
      </node>
    </node>
    <node begin="15" end="16" frame="punct(punt)" id="24" lcat="punct" lemma="." pos="punct" postag="LET()" pt="let" rel="--" root="." sense="." special="punt" word="."/>
  </node>
  <sentence>De Limburgers noemen het vierjaarlijkse Wereld Muziek Concours in Kerkrade het Wimbledon van de blaasmuziek .</sentence>
  <comments>
    <comment>Q#2|De Limburgers noemen het vierjaarlijkse Wereld Muziek Concours in Kerkrade het Wimbledon van de blaasmuziek .|1|1|4.404125542299996</comment>
  </comments>
</alpino_ds>
