<?xml version="1.0" encoding="UTF-8"?>
<?xml-stylesheet href="corea_corpus.xsl" type="text/xsl"?>
<toplevel>
  <sentence alpsent="WR-P-P-H-0000000073.p.1.s.1.xml"><markable head="utrecht" id="markable_1" ref="empty">UTRECHT</markable> -</sentence>
  <sentence alpsent="WR-P-P-H-0000000073.p.1.s.2.xml"><markable head="h. huisinga" id="markable_2" ref="empty"><markable id="markable_118" ref="empty">NS-topman</markable> H. Huisinga</markable> erkent dat <markable head="aantal" id="markable_3" ref="empty">het groeiend aantal <markable head="treinen" id="markable_4" ref="empty">uitvallende en <markable id="markable_120" ref="empty">vertraagde treinen</markable></markable></markable> onacceptabel is .</sentence>
  <sentence alpsent="WR-P-P-H-0000000073.p.2.s.1.xml"><markable head="dat" id="markable_5" ref="empty">Dat</markable> zegt <markable head="huisinga" id="markable_6" level="reference" mod="no" ref="markable_2" time="none" type="ident">Huisinga</markable> in <markable head="de koppeling" id="markable_7" ref="empty">het personeelsblad De Koppeling</markable> .</sentence>
  <sentence alpsent="WR-P-P-H-0000000073.p.2.s.2.xml"><markable head="hij" id="markable_8" level="reference" mod="no" ref="markable_6" time="none" type="ident">Hij</markable> erkent dat er <markable head="fouten" id="markable_9_a" ref="empty">fouten</markable> zijn gemaakt <markable head="fouten" id="markable_9_b" ref="empty">bij <markable head="uitvoering" id="markable_10" ref="empty">de uitvoering van <markable head="bestemming klant" id="markable_11" ref="empty"><markable id="markable_115" ref="empty">het plan Bestemming Klant</markable> , waarvan <markable head="rondje om de kerk" id="markable_12" ref="empty">het gewraakte &apos; rondje om de kerk</markable> &apos; <markable head="onderdeel" id="markable_13" ref="empty">onderdeel</markable> is</markable></markable></markable> .</sentence>
  <sentence alpsent="WR-P-P-H-0000000073.p.2.s.3.xml">,, <markable head="veranderingen" id="markable_14" level="reference" mod="no" ref="markable_11" time="none" type="bridge">Die veranderingen</markable> kosten bij <markable head="elkaar" id="markable_15" level="reference" mod="no" ref="markable_14" time="none" type="ident">elkaar</markable> <markable head="energie" id="markable_16" ref="empty">meer energie dan <markable head="ik" id="markable_17" level="reference" mod="no" ref="markable_8" time="none" type="ident">ik</markable> vooraf had ingeschat</markable> .</sentence>
  <sentence alpsent="WR-P-P-H-0000000073.p.2.s.4.xml"><markable head="ze" id="markable_18" level="reference" mod="no" ref="markable_14" time="none" type="ident">Ze</markable> hebben <markable head="wissel" id="markable_19" ref="empty">een zware wissel</markable> getrokken op <markable head="medewerkers" id="markable_20" ref="empty"><markable id="markable_116" level="reference" mod="no" ref="markable_2" time="none" type="bridge">onze</markable> medewerkers</markable> en <markable head="basiskwaliteit" id="markable_21" ref="empty"><markable id="markable_117" level="reference" mod="no" ref="markable_2" time="none" type="ident">onze</markable> basiskwaliteit</markable> is op <markable head="niveau" id="markable_22" ref="empty">een onacceptabel laag niveau</markable> gekomen &apos;&apos; , zegt <markable head="huisinga" id="markable_23" level="reference" mod="no" ref="markable_8" time="none" type="ident">Huisinga</markable> .</sentence>
  <sentence alpsent="WR-P-P-H-0000000073.p.3.s.1.xml"><markable head="ns" id="markable_24" level="reference" mod="no" ref="markable_2" time="none" type="bridge">De NS</markable> werken inmiddels aan <markable head="plan" id="markable_25" ref="empty">een nieuw plan van <markable head="aanpak" id="markable_26" ref="empty">aanpak</markable></markable> , <markable id="markable_119" ref="empty">onder <markable head="bestemming klant nu" id="markable_27" ref="empty">de werktitel Bestemming Klant Nu</markable></markable> .</sentence>
  <sentence alpsent="WR-P-P-H-0000000073.p.3.s.2.xml"><markable head="dit" id="markable_28" level="reference" mod="no" ref="markable_25" time="none" type="ident">Dit</markable> moet ertoe leiden dat <markable head="knelpunten" id="markable_29" ref="empty">knelpunten</markable> snel worden opgelost .</sentence>
  <sentence alpsent="WR-P-P-H-0000000073.p.3.s.3.xml"><markable head="personeel" id="markable_30" level="reference" mod="no" ref="markable_20" time="none" type="ident">Het personeel</markable> wordt nadrukkelijk betrokken bij <markable head="maatregelen" id="markable_31" level="reference" mod="no" ref="markable_25" time="none" type="ident">de maatregelen die ,, zo snel mogelijk <markable head="verbeteringen" id="markable_32" ref="empty">merkbare verbeteringen</markable> &apos;&apos; moeten opleveren</markable> .</sentence>
  <sentence alpsent="WR-P-P-H-0000000073.p.4.s.1.xml"><markable head="communicatie" id="markable_33" ref="empty">De communicatie over <markable head="maatregelen" id="markable_34" level="reference" mod="no" ref="markable_31" time="none" type="ident">te nemen maatregelen</markable></markable> liet tot nu toe te wensen over , erkent <markable head="huisinga" id="markable_35" level="reference" mod="no" ref="markable_23" time="none" type="ident">Huisinga</markable> tevens .</sentence>
  <sentence alpsent="WR-P-P-H-0000000073.p.4.s.2.xml">,, Daarom trekken <markable head="we" id="markable_36" level="reference" mod="no" ref="markable_35" time="none" type="ident">we</markable> nu vanaf <markable head="begin" id="markable_37" ref="empty">het eerste begin</markable> bedrijfsbreed met <markable head="elkaar" id="markable_38" ref="empty">elkaar</markable> op .</sentence>
  <sentence alpsent="WR-P-P-H-0000000073.p.4.s.3.xml">Gezamenlijk , zoals <markable head="dat" id="markable_39" ref="empty">dat</markable> ook eigenlijk moet .</sentence>
  <sentence alpsent="WR-P-P-H-0000000073.p.4.s.4.xml"><markable head="dat" id="markable_41" ref="empty">Dat</markable> hebben <markable head="we" id="markable_40" level="reference" mod="no" ref="markable_36" time="none" type="ident">we</markable> tot nu toe te weinig gedaan en <markable head="dat" id="markable_42" ref="empty">dat</markable> moet beter . &apos;&apos;</sentence>
  <sentence alpsent="WR-P-P-H-0000000073.p.4.s.5.xml">Er zijn <markable head="teams" id="markable_43" ref="empty">teams gevormd die <markable head="maatregelen" id="markable_44" level="reference" mod="no" ref="markable_34" time="none" type="ident">mogelijke maatregelen</markable> op <markable head="rijtje" id="markable_45" ref="empty">een rijtje</markable> gaan zetten</markable> .</sentence>
  <sentence alpsent="WR-P-P-H-0000000073.p.5.s.1.xml"><markable head="a. van den berg" id="markable_46" ref="empty">A. van den Berg van <markable head="fnv-bondgenoten" id="markable_47" ref="empty">FNV-Bondgenoten</markable></markable> vindt <markable head="het" id="markable_48" ref="empty">het</markable> op <markable head="zich" id="markable_49" ref="empty">zich</markable> verheugend dat <markable head="ns-top" id="markable_50" level="reference" mod="no" ref="markable_35" time="none" type="ident">de NS-top</markable> <markable head="boetekleed" id="markable_51" ref="empty">het boetekleed</markable> aantrekt .</sentence>
  <sentence alpsent="WR-P-P-H-0000000073.p.5.s.2.xml">,, <markable head="dit" id="markable_53" ref="empty">Dit</markable> moet <markable head="ik" id="markable_52" level="reference" mod="no" ref="markable_46" time="none" type="ident">ik</markable> even verwerken .</sentence>
  <sentence alpsent="WR-P-P-H-0000000073.p.5.s.3.xml"><markable head="erkennen" id="markable_54" ref="empty">Het erkennen van <markable head="fouten" id="markable_55" level="reference" mod="no" ref="markable_9_a,markable_9_b" time="none" type="ident">fouten</markable> door <markable head="ns-directie" id="markable_56" level="reference" mod="no" ref="markable_50" time="none" type="ident">de NS-directie</markable></markable> is <markable head="verschijnsel" id="markable_57" ref="empty">geen alledaags verschijnsel</markable> .</sentence>
  <sentence alpsent="WR-P-P-H-0000000073.p.5.s.4.xml"><markable head="ik" id="markable_58" level="reference" mod="no" ref="markable_52" time="none" type="ident">Ik</markable> ben blij dat <markable head="huisinga" id="markable_59" level="reference" mod="no" ref="markable_35" time="none" type="ident">Huisinga</markable> <markable head="dat" id="markable_60" level="reference" mod="no" ref="markable_54" time="none" type="ident">dat</markable> nu wel doet &apos;&apos; , zei <markable head="hij" id="markable_61" level="reference" mod="no" ref="markable_46" time="none" type="ident">hij</markable> in <markable head="reactie" id="markable_62" ref="empty">een reactie</markable> .</sentence>
  <sentence alpsent="WR-P-P-H-0000000073.p.6.s.1.xml"><markable head="vakbondsbestuurder" id="markable_63" level="reference" mod="no" ref="markable_61" time="none" type="ident">De vakbondsbestuurder</markable> stelt dat <markable head="arbeidsverhoudingen" id="markable_64" ref="empty">de arbeidsverhoudingen bij <markable head="spoorbedrijf" id="markable_65" level="reference" mod="no" ref="markable_24" time="none" type="bridge">het spoorbedrijf</markable></markable> nog altijd verziekt zijn .</sentence>
  <sentence alpsent="WR-P-P-H-0000000073.p.6.s.2.xml"><markable head="herstel" id="markable_66" ref="empty">Herstel van <markable head="vertrouwen" id="markable_67" ref="empty">vertrouwen tussen <markable head="en" id="markable_68" ref="empty"><markable head="leiding" id="markable_69" level="reference" mod="no" ref="markable_56" time="none" type="ident">leiding</markable> en <markable head="personeel" id="markable_70" level="reference" mod="no" ref="markable_30" time="none" type="ident">personeel</markable></markable></markable></markable> is absoluut noodzakelijk .</sentence>
  <sentence alpsent="WR-P-P-H-0000000073.p.6.s.3.xml">,, Op <markable head="vlak" id="markable_72" ref="empty">dat vlak</markable> moet er nog <markable head="wat" id="markable_71" ref="empty">heel wat</markable> gebeuren &apos;&apos; , aldus <markable head="van den berg" id="markable_73" level="reference" mod="no" ref="markable_63" time="none" type="ident">Van den Berg</markable> .</sentence>
  <sentence alpsent="WR-P-P-H-0000000073.p.7.s.1.xml"><markable head="netelenbos" id="markable_74" ref="empty">Minister Netelenbos van <markable head="verkeer" id="markable_75" ref="empty">verkeer</markable></markable> wordt met <markable head="plan" id="markable_76" level="reference" mod="no" ref="markable_25" time="none" type="ident">het plan</markable> op <markable head="wenken" id="markable_77" ref="empty"><markable head="haar" id="markable_78" level="reference" mod="no" ref="markable_74" time="none" type="ident">haar</markable> wenken</markable> bediend .</sentence>
  <sentence alpsent="WR-P-P-H-0000000073.p.7.s.2.xml"><markable head="week" id="markable_79" ref="empty">Vorige week</markable> eiste <markable head="zij" id="markable_80" level="reference" mod="no" ref="markable_74" time="none" type="ident">zij</markable> in <markable head="brief" id="markable_81" ref="empty">een brief aan <markable head="tweede kamer" id="markable_82" ref="empty">de Tweede Kamer</markable></markable> dat <markable head="ns-directie" id="markable_83" level="reference" mod="no" ref="markable_69" time="none" type="ident">de NS-directie</markable> binnen &apos; <markable head="termijn" id="markable_84" ref="empty">zeer afzienbare termijn</markable> &apos; <markable head="vertragingen" id="markable_85" level="reference" mod="no" ref="markable_120" time="none" type="ident">de vertragingen</markable> gaat aanpakken .</sentence>
  <sentence alpsent="WR-P-P-H-0000000073.p.7.s.3.xml"><markable head="zij" id="markable_86" level="reference" mod="no" ref="markable_74" time="none" type="ident">Zij</markable> is ervan overtuigd dat <markable head="ns" id="markable_87" level="reference" mod="no" ref="markable_83" time="none" type="ident">de NS</markable> in <markable head="kwartaal" id="markable_88" ref="empty">het tweede kwartaal</markable> niet beter is gaan werken ten opzichte van <markable head="kwartaal" id="markable_89" ref="empty">het eerste kwartaal</markable> .</sentence>
  <sentence alpsent="WR-P-P-H-0000000073.p.7.s.4.xml">Toen lag <markable head="punctualiteit" id="markable_90" ref="empty">de punctualiteit van <markable head="dienstverlening" id="markable_91" ref="empty">de dienstverlening</markable></markable> al ruim beneden <markable head="norm" id="markable_92" ref="empty">de norm die in <markable head="prestatiecontract" id="markable_93" ref="empty">het prestatiecontract tussen <markable head="en" id="markable_94" ref="empty"><markable head="ns" id="markable_95" level="reference" mod="no" ref="markable_87" time="none" type="ident">de NS</markable> en <markable head="overheid" id="markable_96" level="reference" mod="no" ref="markable_86" time="none" type="ident">de overheid</markable></markable></markable> is vastgelegd</markable> .</sentence>
  <sentence alpsent="WR-P-P-H-0000000073.p.7.s.5.xml">In <markable head="contract" id="markable_97" level="reference" mod="no" ref="markable_93" time="none" type="ident">dat contract</markable> staat dat <markable head="procent" id="markable_98" ref="empty">88 procent van <markable head="treinen" id="markable_99" level="reference" mod="no" ref="markable_95" time="none" type="bridge">de treinen</markable></markable> op <markable head="tijd" id="markable_100" ref="empty">tijd</markable> moeten rijden .</sentence>
  <sentence alpsent="WR-P-P-H-0000000073.p.7.s.6.xml">Als dat <markable head="procent" id="markable_102" ref="empty">meer dan <markable head="drie" id="markable_103" ref="empty">drie</markable> procent naar beneden</markable> afwijkt moet <markable head="ns" id="markable_101" level="reference" mod="no" ref="markable_95" time="none" type="ident">de NS</markable> aan <markable head="eind" id="markable_104" ref="empty">het eind van <markable head="jaar" id="markable_105" ref="empty">het jaar</markable></markable> met <markable head="verbeterplan" id="markable_106" ref="empty">een verbeterplan</markable> komen .</sentence>
  <sentence alpsent="WR-P-P-H-0000000073.p.7.s.7.xml">Maar <markable head="bewindsvrouw" id="markable_107" level="reference" mod="no" ref="markable_86" time="none" type="ident">de bewindsvrouw</markable> wilde daarop niet wachten .</sentence>
  <sentence alpsent="WR-P-P-H-0000000073.p.7.s.8.xml">In <markable head="kwartaal" id="markable_108" ref="empty">het eerste kwartaal</markable> reed <markable head="procent" id="markable_109" ref="empty">83,3 procent van <markable head="treinen" id="markable_110" level="reference" mod="no" ref="markable_95" time="none" type="bridge">de treinen</markable></markable> op <markable head="tijd" id="markable_111" ref="empty">tijd</markable> .</sentence>
  <sentence alpsent="WR-P-P-H-0000000073.p.7.s.9.xml"><markable head="netelenbos" id="markable_112" level="reference" mod="no" ref="markable_107" time="none" type="ident">Netelenbos</markable> denkt dat <markable head="het" id="markable_113" ref="empty">het</markable> in <markable head="kwartaal" id="markable_114" ref="empty">het tweede kwartaal</markable> niet beter wordt .</sentence>
</toplevel>
