<?xml version="1.0" encoding="UTF-8"?>
<?xml-stylesheet href="corea_corpus.xsl" type="text/xsl"?>
<toplevel>
  <sentence alpsent="WR-P-P-H-0000000009.p.1.s.1.xml"><markable head="zondag" id="markable_1">Zondag</markable> in <markable head="paleis" id="markable_2">het presidentiële paleis in <markable head="jakarta" id="markable_3">Jakarta</markable></markable> .</sentence>
  <sentence alpsent="WR-P-P-H-0000000009.p.1.s.2.xml"><markable head="gebouw" id="markable_4">Het koloniale witte gebouw</markable> lijkt <markable head="woonhuis" id="markable_5">een woonhuis als <markable head="andere" id="markable_6">alle andere</markable></markable> , als uit <markable head="ramen" id="markable_7">de open ramen</markable> snoeihard <markable head="janis joplin" id="markable_8">Janis Joplin</markable> klinkt .</sentence>
  <sentence alpsent="WR-P-P-H-0000000009.p.1.s.3.xml">Binnen bedient <markable head="yenny wahid" id="markable_9">dochter Yenny Wahid</markable> <markable head="cd-speler" id="markable_10">de cd-speler</markable> voor <markable head="vader" id="markable_11"><markable head="haar" id="markable_12" level="reference" mod="no" ref="markable_9" time="none" type="ident">haar</markable> vader</markable> .</sentence>
  <sentence alpsent="WR-P-P-H-0000000009.p.1.s.4.xml"><markable head="president" id="markable_13" level="reference" mod="no" ref="markable_11" time="none" type="ident">De bijna blinde president van <markable head="indonesië" id="markable_14">Indonesië</markable></markable> kamt , onhandig , <markable head="haar" id="markable_15"><markable head="zijn" id="markable_16" level="reference" mod="no" ref="markable_13" time="none" type="ident">zijn</markable> haar</markable> terwijl <markable head="hij" id="markable_17" level="reference" mod="no" ref="markable_13" time="none" type="ident">hij</markable> vol <markable head="overgave" id="markable_18">overgave</markable> meezingt met <markable head="zangeres" id="markable_19" level="reference" mod="no" ref="markable_8" time="none" type="ident">de Amerikaanse zangeres</markable> .</sentence>
  <sentence alpsent="WR-P-P-H-0000000009.p.2.s.1.xml"><markable head="presidenten" id="markable_20">Hoeveel presidenten ter <markable head="wereld" id="markable_21">wereld</markable></markable> laten <markable head="zich" id="markable_22" level="reference" mod="no" ref="markable_20" time="none" type="bound">zich</markable> filmen terwijl <markable head="ze" id="markable_23" level="reference" mod="no" ref="markable_20" time="none" type="bound">ze</markable> in <markable head="bloesje" id="markable_24">een kreukelig bloesje</markable> , onderuitgezakt in <markable head="fauteuil" id="markable_25">een fauteuil</markable> , aan <markable head="ontbijt" id="markable_26">het zondagse ontbijt</markable> zitten ?</sentence>
  <sentence alpsent="WR-P-P-H-0000000009.p.2.s.2.xml"><markable head="het" id="markable_27">Het</markable> is waarschijnlijk tekenend voor <markable head="regeerstijl" id="markable_28">de volstrekt persoonlijke regeerstijl van <markable head="abdurrahman wahid" id="markable_29" level="reference" mod="no" ref="markable_13" time="none" type="ident">president Abdurrahman Wahid</markable></markable> dat <markable head="hij" id="markable_30" level="reference" mod="no" ref="markable_29" time="none" type="ident">hij</markable> <markable head="curtis levy" id="markable_31">de Australische filmmaker Curtis Levy</markable> <markable head="toestemming" id="markable_32">toestemming gaf <markable head="hem" id="markable_33" level="reference" mod="no" ref="markable_30" time="none" type="ident">hem</markable> <markable head="maanden" id="markable_34">vier maanden</markable> te volgen met <markable head="videocamera" id="markable_35">een videocamera</markable></markable> .</sentence>
  <sentence alpsent="WR-P-P-H-0000000009.p.2.s.3.xml"><markable head="levy" id="markable_36" level="reference" mod="no" ref="markable_31" time="none" type="ident">Levy</markable> werd ontvangen als <markable head="vriend" id="markable_37" level="reference" mod="no" ref="markable_36" time="none" type="pred">een oude vriend</markable> .</sentence>
  <sentence alpsent="WR-P-P-H-0000000009.p.2.s.4.xml"><markable head="jaar" id="markable_38">Tien jaar</markable> eerder maakte <markable head="hij" id="markable_39" level="reference" mod="no" ref="markable_36" time="none" type="ident">hij</markable> ook al eens <markable head="documentaire" id="markable_40">een documentaire over <markable head="wahid" id="markable_41" level="reference" mod="no" ref="markable_33" time="none" type="ident">Wahid</markable></markable> .</sentence>
  <sentence alpsent="WR-P-P-H-0000000009.p.3.s.1.xml"><markable head="wahid" id="markable_42" level="reference" mod="no" ref="markable_41" time="none" type="ident">Wahid</markable> neemt <markable head="ambt" id="markable_43"><markable head="zijn" id="markable_44" level="reference" mod="no" ref="markable_42" time="none" type="ident">zijn</markable> ambt</markable> ogenschijnlijk weinig serieus .</sentence>
  <sentence alpsent="WR-P-P-H-0000000009.p.3.s.2.xml"><markable head="hij" id="markable_45" level="reference" mod="no" ref="markable_42" time="none" type="ident">Hij</markable> neemt van <markable head="reizen" id="markable_46"><markable head="zijn" id="markable_47" level="reference" mod="no" ref="markable_45" time="none" type="ident">zijn</markable> buitenlandse reizen</markable> <markable head="t-shirts" id="markable_48">t-shirts</markable> mee als <markable head="souvenir" id="markable_49">souvenir</markable> .</sentence>
  <sentence alpsent="WR-P-P-H-0000000009.p.3.s.3.xml"><markable head="paleis" id="markable_50">Het paleis</markable> lijkt <markable head="nil" id="markable_51"><markable head="inval" id="markable_52">een zoete inval</markable> , <markable head="boel" id="markable_53">een gezellige boel</markable></markable> .</sentence>
  <sentence alpsent="WR-P-P-H-0000000009.p.3.s.4.xml">Grappend en grollend verpoost <markable head="wahid" id="markable_54" level="reference" mod="no" ref="markable_45" time="none" type="ident">Wahid</markable> <markable head="zich" id="markable_55">zich</markable> met <markable head="gasten" id="markable_56"><markable head="zijn" id="markable_57" level="reference" mod="no" ref="markable_54" time="none" type="ident">zijn</markable> gasten</markable> .</sentence>
  <sentence alpsent="WR-P-P-H-0000000009.p.3.s.5.xml">Om <markable head="moppen" id="markable_59"><markable head="zijn" id="markable_60" level="reference" mod="no" ref="markable_54" time="none" type="ident">zijn</markable> moppen</markable> moet <markable head="hij" id="markable_58" level="reference" mod="no" ref="markable_54" time="none" type="ident">hij</markable> zelf nog het hardst lachen .</sentence>
  <sentence alpsent="WR-P-P-H-0000000009.p.3.s.6.xml">,, <markable head="ik" id="markable_61" level="reference" mod="no" ref="markable_58" time="none" type="ident">Ik</markable> maak <markable head="iedereen" id="markable_62">iedereen</markable> gek .</sentence>
  <sentence alpsent="WR-P-P-H-0000000009.p.3.s.7.xml"><markable head="hahaha" id="markable_63">Hahaha</markable> .</sentence>
  <sentence alpsent="WR-P-P-H-0000000009.p.3.s.8.xml">Leuk hè ? &apos;&apos; , giert <markable head="flapuit" id="markable_64" level="reference" mod="no" ref="markable_58" time="none" type="ident">de flapuit die aan het hoofd staat van <markable head="land" id="markable_65">een land met <markable head="miljoen" id="markable_66">220 miljoen <markable head="inwoners" id="markable_67">inwoners</markable></markable></markable></markable> .</sentence>
  <sentence alpsent="WR-P-P-H-0000000009.p.4.s.1.xml">Maar <markable head="schijn" id="markable_68">schijn</markable> bedriegt .</sentence>
  <sentence alpsent="WR-P-P-H-0000000009.p.4.s.2.xml"><markable head="high noon in jakarta" id="markable_70">De documentaire &apos; High Noon in Jakarta &apos; ( genoemd naar <markable head="een" id="markable_71">een van <markable head="speelfilms" id="markable_72">de favoriete speelfilms van <markable head="wahid" id="markable_73">Wahid</markable></markable></markable></markable> ) toont eens te <markable head="meer" id="markable_69">meer</markable> dat <markable head="moslimgeleerde" id="markable_74" level="reference" mod="no" ref="markable_64" time="none" type="ident">de Javaanse moslimgeleerde</markable> <markable head="boeienkoning" id="markable_75" level="reference" mod="no" ref="markable_74" time="none" type="pred">een politieke boeienkoning</markable> is .</sentence>
  <sentence alpsent="WR-P-P-H-0000000009.p.4.s.3.xml"><markable head="levy" id="markable_76" level="reference" mod="no" ref="markable_36" time="none" type="ident">Levy</markable> volgde <markable head="wahid" id="markable_77" level="reference" mod="no" ref="markable_74" time="none" type="ident">Wahid</markable> in <markable head="periode" id="markable_78">een dramatische periode</markable> .</sentence>
  <sentence alpsent="WR-P-P-H-0000000009.p.4.s.4.xml"><markable head="film" id="markable_79" level="reference" mod="no" ref="markable_70" time="none" type="ident">De film</markable> is <markable head="voorjaar" id="markable_80">vorig voorjaar</markable> opgenomen toen <markable head="wahid" id="markable_81" level="reference" mod="no" ref="markable_77" time="none" type="ident">Wahid</markable> bezig was <markable head="macht" id="markable_82">de macht te breken van zowel <markable head="wiranto" id="markable_83">de beruchte generaal Wiranto</markable> als van <markable head="soeharto" id="markable_84">ex-president Soeharto</markable></markable> .</sentence>
  <sentence alpsent="WR-P-P-H-0000000009.p.5.s.1.xml"><markable head="hij" id="markable_85" level="reference" mod="no" ref="markable_81" time="none" type="ident">Hij</markable> doet <markable head="dat" id="markable_86" level="reference" mod="no" ref="markable_82" time="none" type="ident">dat</markable> fenomenaal .</sentence>
  <sentence alpsent="WR-P-P-H-0000000009.p.5.s.2.xml"><markable head="jaar" id="markable_87">Zelfs een jaar</markable> later , terwijl <markable head="afloop" id="markable_88" level="reference" mod="no" ref="markable_79" time="none" type="bridge">de afloop</markable> bekend is , ontrolt <markable head="documentaire" id="markable_89" level="reference" mod="no" ref="markable_79" time="none" type="ident">de documentaire</markable> <markable head="zich" id="markable_90">zich</markable> als <markable head="thriller" id="markable_91" level="reference" mod="no" ref="markable_89" time="none" type="pred">een spannende thriller</markable> .</sentence>
  <sentence alpsent="WR-P-P-H-0000000009.p.5.s.3.xml">Dramatisch is <markable head="moment" id="markable_92">het moment dat <markable head="wahid" id="markable_93" level="reference" mod="no" ref="markable_85" time="none" type="ident">Wahid</markable> terugkeert van <markable head="reis" id="markable_94">een buitenlandse reis van <markable head="dagen" id="markable_95">16 dagen</markable> langs <markable head="landen" id="markable_96">13 landen</markable></markable> , en op <markable head="vliegveld" id="markable_97">het vliegveld</markable> wordt opgewacht door <markable head="wiranto" id="markable_98" level="reference" mod="no" ref="markable_83" time="none" type="ident">een onverstoorbare Wiranto</markable></markable> .</sentence>
  <sentence alpsent="WR-P-P-H-0000000009.p.5.s.4.xml"><markable head="die" id="markable_99" level="reference" mod="no" ref="markable_98" time="none" type="ident"><markable id="markable_124_a" ref="empty">Die</markable></markable> weigert <markable head="ontslag" id="markable_100">ontslag</markable> te nemen , zoals <markable head="wahid" id="markable_101" level="reference" mod="no" ref="markable_93" time="none" type="ident"><markable id="markable_124_b" ref="empty">Wahid</markable></markable> heeft bevolen .</sentence>
  <sentence alpsent="WR-P-P-H-0000000009.p.5.s.5.xml"><markable head="giganten" id="markable_102" level="reference" mod="no" ref="markable_124_a,markable_124_b" time="none" type="ident">De twee giganten</markable> schudden <markable head="elkaar" id="markable_103" level="reference" mod="no" ref="markable_102" time="none" type="bound">elkaar</markable> glimlachend <markable head="hand" id="markable_104">de hand</markable> .</sentence>
  <sentence alpsent="WR-P-P-H-0000000009.p.5.s.6.xml">Maar <markable head="dag" id="markable_106">een dag</markable> later heeft <markable head="wahid" id="markable_105" level="reference" mod="no" ref="markable_101" time="none" type="ident">Wahid</markable> wél gewonnen .</sentence>
  <sentence alpsent="WR-P-P-H-0000000009.p.6.s.1.xml"><markable head="levy" id="markable_107" level="reference" mod="no" ref="markable_76" time="none" type="ident">Levy</markable> filmde <markable head="wahid" id="markable_108" level="reference" mod="no" ref="markable_105" time="none" type="ident">Wahid</markable> op <markable head="hoogtepunt" id="markable_109">het hoogtepunt van <markable head="macht" id="markable_110"><markable head="zijn" id="markable_111" level="reference" mod="no" ref="markable_108" time="none" type="ident">zijn</markable> macht</markable></markable> , <markable head="periode" id="markable_112" level="reference" mod="no" ref="markable_109" time="none" type="pred">een periode die maar kort heeft geduurd</markable> .</sentence>
  <sentence alpsent="WR-P-P-H-0000000009.p.6.s.2.xml">In <markable head="jaar" id="markable_113">het jaar dat volgde</markable> , raakte <markable head="wahid" id="markable_114" level="reference" mod="no" ref="markable_108" time="none" type="ident">Wahid</markable> in <markable head="problemen" id="markable_115">grote problemen</markable> .</sentence>
  <sentence alpsent="WR-P-P-H-0000000009.p.6.s.3.xml">Zou <markable head="levy" id="markable_116" level="reference" mod="no" ref="markable_107" time="none" type="ident">Levy</markable> opnieuw zijn uitgenodigd , <markable head="zomer" id="markable_117">deze zomer</markable> , als <markable head="wahid" id="markable_118" level="reference" mod="no" ref="markable_114" time="none" type="ident">Wahid</markable> door <markable head="indonesische volkscongres" id="markable_119">het Indonesische Volkscongres</markable> zo goed als zeker zal worden afgezet ?</sentence>
  <sentence alpsent="WR-P-P-H-0000000009.p.7.s.1.xml"><markable head="wahid" id="markable_120" level="reference" mod="no" ref="markable_118" time="none" type="ident">De Indonesische president Wahid</markable> .</sentence>
  <sentence alpsent="WR-P-P-H-0000000009.p.8.s.1.xml">&apos; <markable head="wahid - high noon in jakarta" id="markable_121" level="reference" mod="no" ref="markable_89" time="none" type="ident">Wahid - High Noon in Jakarta</markable> &apos; , <markable head="20.56 uur" id="markable_122">20.56 uur</markable> , <markable head="nederland 3" id="markable_123">Nederland 3</markable> .</sentence>
</toplevel>
